ogs5py/__init__.py
ogs5py/_version.py
ogs5py/ogs.py
ogs5py/fileclasses/__init__.py
ogs5py/fileclasses/base.py
ogs5py/fileclasses/asc/__init__.py
ogs5py/fileclasses/asc/core.py
ogs5py/fileclasses/bc/__init__.py
ogs5py/fileclasses/bc/core.py
ogs5py/fileclasses/cct/__init__.py
ogs5py/fileclasses/cct/core.py
ogs5py/fileclasses/ddc/__init__.py
ogs5py/fileclasses/ddc/core.py
ogs5py/fileclasses/fct/__init__.py
ogs5py/fileclasses/fct/core.py
ogs5py/fileclasses/gem/__init__.py
ogs5py/fileclasses/gem/core.py
ogs5py/fileclasses/gli/__init__.py
ogs5py/fileclasses/gli/checker.py
ogs5py/fileclasses/gli/core.py
ogs5py/fileclasses/gli/generator.py
ogs5py/fileclasses/gli/tools.py
ogs5py/fileclasses/ic/__init__.py
ogs5py/fileclasses/ic/core.py
ogs5py/fileclasses/krc/__init__.py
ogs5py/fileclasses/krc/core.py
ogs5py/fileclasses/mcp/__init__.py
ogs5py/fileclasses/mcp/core.py
ogs5py/fileclasses/mfp/__init__.py
ogs5py/fileclasses/mfp/core.py
ogs5py/fileclasses/mmp/__init__.py
ogs5py/fileclasses/mmp/core.py
ogs5py/fileclasses/mpd/__init__.py
ogs5py/fileclasses/mpd/core.py
ogs5py/fileclasses/msh/__init__.py
ogs5py/fileclasses/msh/checker.py
ogs5py/fileclasses/msh/core.py
ogs5py/fileclasses/msh/generator.py
ogs5py/fileclasses/msh/gmsh.py
ogs5py/fileclasses/msh/helpers.py
ogs5py/fileclasses/msh/msh_io.py
ogs5py/fileclasses/msh/tools.py
ogs5py/fileclasses/msh/viewer.py
ogs5py/fileclasses/msp/__init__.py
ogs5py/fileclasses/msp/core.py
ogs5py/fileclasses/num/__init__.py
ogs5py/fileclasses/num/core.py
ogs5py/fileclasses/out/__init__.py
ogs5py/fileclasses/out/core.py
ogs5py/fileclasses/pcs/__init__.py
ogs5py/fileclasses/pcs/core.py
ogs5py/fileclasses/pct/__init__.py
ogs5py/fileclasses/pct/core.py
ogs5py/fileclasses/pqc/__init__.py
ogs5py/fileclasses/pqc/core.py
ogs5py/fileclasses/rei/__init__.py
ogs5py/fileclasses/rei/core.py
ogs5py/fileclasses/rfd/__init__.py
ogs5py/fileclasses/rfd/core.py
ogs5py/fileclasses/st/__init__.py
ogs5py/fileclasses/st/core.py
ogs5py/fileclasses/tim/__init__.py
ogs5py-1.3.0.dist-info/METADATA
ogs5py-1.3.0.dist-info/WHEEL
ogs5py-1.3.0.dist-info/licenses/AUTHORS.md
ogs5py-1.3.0.dist-info/licenses/LICENSE
ogs5py-1.3.0.dist-info/RECORD
