Metadata-Version: 2.1
Name: ogs5py
Version: 1.3.0
Summary: ogs5py: a python API for OpenGeoSys5
Project-URL: Homepage, https://geostat-framework.org/#ogs5py
Project-URL: Documentation, https://ogs5py.readthedocs.io
Project-URL: Source, https://github.com/GeoStat-Framework/ogs5py
Project-URL: Tracker, https://github.com/GeoStat-Framework/ogs5py/issues
Project-URL: Changelog, https://github.com/GeoStat-Framework/ogs5py/blob/main/CHANGELOG.md
Project-URL: Conda-Forge, https://anaconda.org/conda-forge/ogs5py
Author-email: "Sebastian Müller, Falk Heße" <info@geostat-framework.org>
License-Expression: MIT
License-File: AUTHORS.md
License-File: LICENSE
Classifier: Development Status :: 5 - Production/Stable
Classifier: Intended Audience :: Developers
Classifier: Intended Audience :: Education
Classifier: Intended Audience :: End Users/Desktop
Classifier: Intended Audience :: Science/Research
Classifier: License :: OSI Approved :: MIT License
Classifier: Natural Language :: English
Classifier: Operating System :: MacOS
Classifier: Operating System :: Microsoft
Classifier: Operating System :: Unix
Classifier: Programming Language :: Python
Classifier: Programming Language :: Python :: 3
Classifier: Programming Language :: Python :: 3 :: Only
Classifier: Programming Language :: Python :: 3.7
Classifier: Programming Language :: Python :: 3.8
Classifier: Programming Language :: Python :: 3.9
Classifier: Programming Language :: Python :: 3.10
Classifier: Programming Language :: Python :: 3.11
Classifier: Topic :: Scientific/Engineering
Classifier: Topic :: Scientific/Engineering :: GIS
Classifier: Topic :: Scientific/Engineering :: Hydrology
Classifier: Topic :: Scientific/Engineering :: Mathematics
Classifier: Topic :: Scientific/Engineering :: Physics
Classifier: Topic :: Utilities
Requires-Python: >=3.7
Requires-Dist: lxml>=4
Requires-Dist: meshio>=4
Requires-Dist: numpy>=1.14.5
Requires-Dist: pandas>=0.23.2
Requires-Dist: pexpect>=4
Requires-Dist: vtk>=9
Provides-Extra: check
Requires-Dist: black<24,>=23; extra == 'check'
Requires-Dist: isort[colors]<6; extra == 'check'
Provides-Extra: doc
Requires-Dist: m2r2>=0.2.8; extra == 'doc'
Requires-Dist: numpydoc>=1.1; extra == 'doc'
Requires-Dist: sphinx-rtd-theme>=1; extra == 'doc'
Requires-Dist: sphinx>=4; extra == 'doc'
Provides-Extra: gmsh
Requires-Dist: gmsh; extra == 'gmsh'
Provides-Extra: show
Requires-Dist: mayavi; extra == 'show'
Provides-Extra: test
Requires-Dist: pytest-cov>=3; extra == 'test'
